{
  "a_comp_cor_00": {
    "CumulativeVarianceExplained": 0.0621144281,
    "Mask": "combined",
    "Method": "aCompCor",
    "Retained": true,
    "SingularValue": 109.7371787576,
    "VarianceExplained": 0.0621144281
  },
  "a_comp_cor_01": {
    "CumulativeVarianceExplained": 0.1157417726,
    "Mask": "combined",
    "Method": "aCompCor",
    "Retained": true,
    "SingularValue": 101.964898576,
    "VarianceExplained": 0.0536273445
  },
  "a_comp_cor_02": {
    "CumulativeVarianceExplained": 0.1578041544,
    "Mask": "combined",
    "Method": "aCompCor",
    "Retained": true,
    "SingularValue": 90.3034776913,
    "VarianceExplained": 0.0420623818
  },
  "a_comp_cor_03": {
    "CumulativeVarianceExplained": 0.1960390566,
    "Mask": "combined",
    "Method": "aCompCor",
    "Retained": true,
    "SingularValue": 86.096904474,
    "VarianceExplained": 0.0382349022
  },
  "a_comp_cor_04": {
    "CumulativeVarianceExplained": 0.2332980179,
    "Mask": "combined",
    "Method": "aCompCor",
    "Retained": true,
    "SingularValue": 84.9909956771,
    "VarianceExplained": 0.0372589613
  },
  "a_comp_cor_05": {
    "CumulativeVarianceExplained": 0.2610323053,
    "Mask": "combined",
    "Method": "aCompCor",
    "Retained": true,
    "SingularValue": 73.3273602787,
    "VarianceExplained": 0.0277342874
  },
  "a_comp_cor_06": {
    "CumulativeVarianceExplained": 0.2849733521,
    "Mask": "combined",
    "Method": "aCompCor",
    "Retained": true,
    "SingularValue": 68.1285447897,
    "VarianceExplained": 0.0239410467
  },
  "a_comp_cor_07": {
    "CumulativeVarianceExplained": 0.3062757641,
    "Mask": "combined",
    "Method": "aCompCor",
    "Retained": true,
    "SingularValue": 64.2646188074,
    "VarianceExplained": 0.0213024121
  },
  "a_comp_cor_08": {
    "CumulativeVarianceExplained": 0.3256451158,
    "Mask": "combined",
    "Method": "aCompCor",
    "Retained": true,
    "SingularValue": 61.2794823334,
    "VarianceExplained": 0.0193693517
  },
  "a_comp_cor_09": {
    "CumulativeVarianceExplained": 0.3439734856,
    "Mask": "combined",
    "Method": "aCompCor",
    "Retained": true,
    "SingularValue": 59.6100470159,
    "VarianceExplained": 0.0183283698
  },
  "a_comp_cor_10": {
    "CumulativeVarianceExplained": 0.3592268117,
    "Mask": "combined",
    "Method": "aCompCor",
    "Retained": true,
    "SingularValue": 54.3800774669,
    "VarianceExplained": 0.015253326
  },
  "a_comp_cor_11": {
    "CumulativeVarianceExplained": 0.3728998205,
    "Mask": "combined",
    "Method": "aCompCor",
    "Retained": true,
    "SingularValue": 51.4860522222,
    "VarianceExplained": 0.0136730089
  },
  "a_comp_cor_12": {
    "CumulativeVarianceExplained": 0.3857948737,
    "Mask": "combined",
    "Method": "aCompCor",
    "Retained": true,
    "SingularValue": 49.9998975907,
    "VarianceExplained": 0.0128950532
  },
  "a_comp_cor_13": {
    "CumulativeVarianceExplained": 0.3974979394,
    "Mask": "combined",
    "Method": "aCompCor",
    "Retained": true,
    "SingularValue": 47.6329377006,
    "VarianceExplained": 0.0117030657
  },
  "a_comp_cor_14": {
    "CumulativeVarianceExplained": 0.4089191944,
    "Mask": "combined",
    "Method": "aCompCor",
    "Retained": true,
    "SingularValue": 47.0559405333,
    "VarianceExplained": 0.0114212549
  },
  "a_comp_cor_15": {
    "CumulativeVarianceExplained": 0.4197149361,
    "Mask": "combined",
    "Method": "aCompCor",
    "Retained": true,
    "SingularValue": 45.7492297978,
    "VarianceExplained": 0.0107957417
  },
  "a_comp_cor_16": {
    "CumulativeVarianceExplained": 0.4297646033,
    "Mask": "combined",
    "Method": "aCompCor",
    "Retained": true,
    "SingularValue": 44.1401075082,
    "VarianceExplained": 0.0100496673
  },
  "a_comp_cor_17": {
    "CumulativeVarianceExplained": 0.4393439517,
    "Mask": "combined",
    "Method": "aCompCor",
    "Retained": true,
    "SingularValue": 43.0948655061,
    "VarianceExplained": 0.0095793484
  },
  "a_comp_cor_18": {
    "CumulativeVarianceExplained": 0.4484805752,
    "Mask": "combined",
    "Method": "aCompCor",
    "Retained": true,
    "SingularValue": 42.0872364418,
    "VarianceExplained": 0.0091366235
  },
  "a_comp_cor_19": {
    "CumulativeVarianceExplained": 0.4572533444,
    "Mask": "combined",
    "Method": "aCompCor",
    "Retained": true,
    "SingularValue": 41.2406875589,
    "VarianceExplained": 0.0087727692
  },
  "a_comp_cor_20": {
    "CumulativeVarianceExplained": 0.4653940677,
    "Mask": "combined",
    "Method": "aCompCor",
    "Retained": true,
    "SingularValue": 39.7272991798,
    "VarianceExplained": 0.0081407233
  },
  "a_comp_cor_21": {
    "CumulativeVarianceExplained": 0.4734909144,
    "Mask": "combined",
    "Method": "aCompCor",
    "Retained": true,
    "SingularValue": 39.6200942146,
    "VarianceExplained": 0.0080968467
  },
  "a_comp_cor_22": {
    "CumulativeVarianceExplained": 0.4810340558,
    "Mask": "combined",
    "Method": "aCompCor",
    "Retained": true,
    "SingularValue": 38.2413901563,
    "VarianceExplained": 0.0075431415
  },
  "a_comp_cor_23": {
    "CumulativeVarianceExplained": 0.4885311693,
    "Mask": "combined",
    "Method": "aCompCor",
    "Retained": true,
    "SingularValue": 38.1245377805,
    "VarianceExplained": 0.0074971135
  },
  "a_comp_cor_24": {
    "CumulativeVarianceExplained": 0.4957770933,
    "Mask": "combined",
    "Method": "aCompCor",
    "Retained": true,
    "SingularValue": 37.4804186806,
    "VarianceExplained": 0.007245924
  },
  "a_comp_cor_25": {
    "CumulativeVarianceExplained": 0.5029155203,
    "Mask": "combined",
    "Method": "aCompCor",
    "Retained": true,
    "SingularValue": 37.2013590965,
    "VarianceExplained": 0.007138427
  },
  "aroma_motion_1": {
    "CSFFraction": 0.0,
    "EdgeFraction": 0.32,
    "HighFrequencyContent": 0.12,
    "MaximumRpCorrelation": 0.38,
    "Method": {
      "Name": "ICA-AROMA",
      "Version": "0.4.5"
    },
    "ModelVarianceExplained": 0.0405434847,
    "MotionNoise": false,
    "TotalVarianceExplained": 0.0366451692
  },
  "aroma_motion_10": {
    "CSFFraction": 0.11,
    "EdgeFraction": 0.48,
    "HighFrequencyContent": 0.47,
    "MaximumRpCorrelation": 0.23,
    "Method": {
      "Name": "ICA-AROMA",
      "Version": "0.4.5"
    },
    "ModelVarianceExplained": 0.0241808211,
    "MotionNoise": true,
    "TotalVarianceExplained": 0.0218557997
  },
  "aroma_motion_11": {
    "CSFFraction": 0.01,
    "EdgeFraction": 0.6,
    "HighFrequencyContent": 0.17,
    "MaximumRpCorrelation": 0.77,
    "Method": {
      "Name": "ICA-AROMA",
      "Version": "0.4.5"
    },
    "ModelVarianceExplained": 0.0232542838,
    "MotionNoise": true,
    "TotalVarianceExplained": 0.0210183504
  },
  "aroma_motion_12": {
    "CSFFraction": 0.01,
    "EdgeFraction": 0.81,
    "HighFrequencyContent": 0.4,
    "MaximumRpCorrelation": 0.55,
    "Method": {
      "Name": "ICA-AROMA",
      "Version": "0.4.5"
    },
    "ModelVarianceExplained": 0.0227218756,
    "MotionNoise": true,
    "TotalVarianceExplained": 0.020537134
  },
  "aroma_motion_13": {
    "CSFFraction": 0.12,
    "EdgeFraction": 0.43,
    "HighFrequencyContent": 0.5,
    "MaximumRpCorrelation": 0.22,
    "Method": {
      "Name": "ICA-AROMA",
      "Version": "0.4.5"
    },
    "ModelVarianceExplained": 0.0224172111,
    "MotionNoise": true,
    "TotalVarianceExplained": 0.0202617634
  },
  "aroma_motion_14": {
    "CSFFraction": 0.01,
    "EdgeFraction": 0.79,
    "HighFrequencyContent": 0.26,
    "MaximumRpCorrelation": 0.39,
    "Method": {
      "Name": "ICA-AROMA",
      "Version": "0.4.5"
    },
    "ModelVarianceExplained": 0.0223796546,
    "MotionNoise": true,
    "TotalVarianceExplained": 0.020227818
  },
  "aroma_motion_15": {
    "CSFFraction": 0.08,
    "EdgeFraction": 0.56,
    "HighFrequencyContent": 0.5,
    "MaximumRpCorrelation": 0.22,
    "Method": {
      "Name": "ICA-AROMA",
      "Version": "0.4.5"
    },
    "ModelVarianceExplained": 0.0209705376,
    "MotionNoise": true,
    "TotalVarianceExplained": 0.0189541897
  },
  "aroma_motion_16": {
    "CSFFraction": 0.01,
    "EdgeFraction": 0.7,
    "HighFrequencyContent": 0.02,
    "MaximumRpCorrelation": 0.28,
    "Method": {
      "Name": "ICA-AROMA",
      "Version": "0.4.5"
    },
    "ModelVarianceExplained": 0.0207457137,
    "MotionNoise": true,
    "TotalVarianceExplained": 0.0187509829
  },
  "aroma_motion_17": {
    "CSFFraction": 0.02,
    "EdgeFraction": 0.4,
    "HighFrequencyContent": 0.38,
    "MaximumRpCorrelation": 0.36,
    "Method": {
      "Name": "ICA-AROMA",
      "Version": "0.4.5"
    },
    "ModelVarianceExplained": 0.0206250622,
    "MotionNoise": true,
    "TotalVarianceExplained": 0.0186419322
  },
  "aroma_motion_18": {
    "CSFFraction": 0.09,
    "EdgeFraction": 0.44,
    "HighFrequencyContent": 0.52,
    "MaximumRpCorrelation": 0.21,
    "Method": {
      "Name": "ICA-AROMA",
      "Version": "0.4.5"
    },
    "ModelVarianceExplained": 0.0193286384,
    "MotionNoise": true,
    "TotalVarianceExplained": 0.0174701615
  },
  "aroma_motion_19": {
    "CSFFraction": 0.02,
    "EdgeFraction": 0.2,
    "HighFrequencyContent": 0.18,
    "MaximumRpCorrelation": 0.41,
    "Method": {
      "Name": "ICA-AROMA",
      "Version": "0.4.5"
    },
    "ModelVarianceExplained": 0.0192745248,
    "MotionNoise": false,
    "TotalVarianceExplained": 0.017421251
  },
  "aroma_motion_2": {
    "CSFFraction": 0.01,
    "EdgeFraction": 0.7,
    "HighFrequencyContent": 0.19,
    "MaximumRpCorrelation": 0.54,
    "Method": {
      "Name": "ICA-AROMA",
      "Version": "0.4.5"
    },
    "ModelVarianceExplained": 0.0365660624,
    "MotionNoise": true,
    "TotalVarianceExplained": 0.0330501819
  },
  "aroma_motion_20": {
    "CSFFraction": 0.06,
    "EdgeFraction": 0.37,
    "HighFrequencyContent": 0.19,
    "MaximumRpCorrelation": 0.41,
    "Method": {
      "Name": "ICA-AROMA",
      "Version": "0.4.5"
    },
    "ModelVarianceExplained": 0.018606596,
    "MotionNoise": false,
    "TotalVarianceExplained": 0.0168175446
  },
  "aroma_motion_21": {
    "CSFFraction": 0.0,
    "EdgeFraction": 0.57,
    "HighFrequencyContent": 0.31,
    "MaximumRpCorrelation": 0.37,
    "Method": {
      "Name": "ICA-AROMA",
      "Version": "0.4.5"
    },
    "ModelVarianceExplained": 0.0185690889,
    "MotionNoise": false,
    "TotalVarianceExplained": 0.0167836438
  },
  "aroma_motion_22": {
    "CSFFraction": 0.0,
    "EdgeFraction": 0.42,
    "HighFrequencyContent": 0.06,
    "MaximumRpCorrelation": 0.41,
    "Method": {
      "Name": "ICA-AROMA",
      "Version": "0.4.5"
    },
    "ModelVarianceExplained": 0.0183749343,
    "MotionNoise": false,
    "TotalVarianceExplained": 0.0166081574
  },
  "aroma_motion_23": {
    "CSFFraction": 0.02,
    "EdgeFraction": 0.42,
    "HighFrequencyContent": 0.13,
    "MaximumRpCorrelation": 0.37,
    "Method": {
      "Name": "ICA-AROMA",
      "Version": "0.4.5"
    },
    "ModelVarianceExplained": 0.0179106702,
    "MotionNoise": false,
    "TotalVarianceExplained": 0.016188533
  },
  "aroma_motion_24": {
    "CSFFraction": 0.0,
    "EdgeFraction": 0.37,
    "HighFrequencyContent": 0.22,
    "MaximumRpCorrelation": 0.51,
    "Method": {
      "Name": "ICA-AROMA",
      "Version": "0.4.5"
    },
    "ModelVarianceExplained": 0.0178686677,
    "MotionNoise": false,
    "TotalVarianceExplained": 0.0161505691
  },
  "aroma_motion_25": {
    "CSFFraction": 0.05,
    "EdgeFraction": 0.52,
    "HighFrequencyContent": 0.36,
    "MaximumRpCorrelation": 0.36,
    "Method": {
      "Name": "ICA-AROMA",
      "Version": "0.4.5"
    },
    "ModelVarianceExplained": 0.0174965188,
    "MotionNoise": true,
    "TotalVarianceExplained": 0.0158142029
  },
  "aroma_motion_26": {
    "CSFFraction": 0.0,
    "EdgeFraction": 0.29,
    "HighFrequencyContent": 0.03,
    "MaximumRpCorrelation": 0.36,
    "Method": {
      "Name": "ICA-AROMA",
      "Version": "0.4.5"
    },
    "ModelVarianceExplained": 0.0174292145,
    "MotionNoise": false,
    "TotalVarianceExplained": 0.01575337
  },
  "aroma_motion_27": {
    "CSFFraction": 0.11,
    "EdgeFraction": 0.51,
    "HighFrequencyContent": 0.49,
    "MaximumRpCorrelation": 0.26,
    "Method": {
      "Name": "ICA-AROMA",
      "Version": "0.4.5"
    },
    "ModelVarianceExplained": 0.0170543662,
    "MotionNoise": true,
    "TotalVarianceExplained": 0.0154145639
  },
  "aroma_motion_28": {
    "CSFFraction": 0.0,
    "EdgeFraction": 0.9,
    "HighFrequencyContent": 0.52,
    "MaximumRpCorrelation": 0.53,
    "Method": {
      "Name": "ICA-AROMA",
      "Version": "0.4.5"
    },
    "ModelVarianceExplained": 0.0169677755,
    "MotionNoise": true,
    "TotalVarianceExplained": 0.015336299
  },
  "aroma_motion_29": {
    "CSFFraction": 0.0,
    "EdgeFraction": 0.64,
    "HighFrequencyContent": 0.12,
    "MaximumRpCorrelation": 0.57,
    "Method": {
      "Name": "ICA-AROMA",
      "Version": "0.4.5"
    },
    "ModelVarianceExplained": 0.0169423032,
    "MotionNoise": true,
    "TotalVarianceExplained": 0.0153132759
  },
  "aroma_motion_3": {
    "CSFFraction": 0.0,
    "EdgeFraction": 0.27,
    "HighFrequencyContent": 0.17,
    "MaximumRpCorrelation": 0.33,
    "Method": {
      "Name": "ICA-AROMA",
      "Version": "0.4.5"
    },
    "ModelVarianceExplained": 0.0339045392,
    "MotionNoise": false,
    "TotalVarianceExplained": 0.030644568
  },
  "aroma_motion_30": {
    "CSFFraction": 0.0,
    "EdgeFraction": 0.24,
    "HighFrequencyContent": 0.09,
    "MaximumRpCorrelation": 0.26,
    "Method": {
      "Name": "ICA-AROMA",
      "Version": "0.4.5"
    },
    "ModelVarianceExplained": 0.0169383418,
    "MotionNoise": false,
    "TotalVarianceExplained": 0.0153096954
  },
  "aroma_motion_31": {
    "CSFFraction": 0.0,
    "EdgeFraction": 0.31,
    "HighFrequencyContent": 0.14,
    "MaximumRpCorrelation": 0.26,
    "Method": {
      "Name": "ICA-AROMA",
      "Version": "0.4.5"
    },
    "ModelVarianceExplained": 0.0166837407,
    "MotionNoise": false,
    "TotalVarianceExplained": 0.0150795746
  },
  "aroma_motion_32": {
    "CSFFraction": 0.01,
    "EdgeFraction": 0.26,
    "HighFrequencyContent": 0.18,
    "MaximumRpCorrelation": 0.21,
    "Method": {
      "Name": "ICA-AROMA",
      "Version": "0.4.5"
    },
    "ModelVarianceExplained": 0.016140395,
    "MotionNoise": false,
    "TotalVarianceExplained": 0.0145884724
  },
  "aroma_motion_33": {
    "CSFFraction": 0.0,
    "EdgeFraction": 0.27,
    "HighFrequencyContent": 0.08,
    "MaximumRpCorrelation": 0.44,
    "Method": {
      "Name": "ICA-AROMA",
      "Version": "0.4.5"
    },
    "ModelVarianceExplained": 0.0159402533,
    "MotionNoise": false,
    "TotalVarianceExplained": 0.0144075745
  },
  "aroma_motion_34": {
    "CSFFraction": 0.01,
    "EdgeFraction": 0.23,
    "HighFrequencyContent": 0.17,
    "MaximumRpCorrelation": 0.44,
    "Method": {
      "Name": "ICA-AROMA",
      "Version": "0.4.5"
    },
    "ModelVarianceExplained": 0.0156576599,
    "MotionNoise": false,
    "TotalVarianceExplained": 0.014152153
  },
  "aroma_motion_35": {
    "CSFFraction": 0.0,
    "EdgeFraction": 0.42,
    "HighFrequencyContent": 0.07,
    "MaximumRpCorrelation": 0.35,
    "Method": {
      "Name": "ICA-AROMA",
      "Version": "0.4.5"
    },
    "ModelVarianceExplained": 0.0156472354,
    "MotionNoise": false,
    "TotalVarianceExplained": 0.0141427308
  },
  "aroma_motion_36": {
    "CSFFraction": 0.01,
    "EdgeFraction": 0.39,
    "HighFrequencyContent": 0.08,
    "MaximumRpCorrelation": 0.38,
    "Method": {
      "Name": "ICA-AROMA",
      "Version": "0.4.5"
    },
    "ModelVarianceExplained": 0.0155611524,
    "MotionNoise": false,
    "TotalVarianceExplained": 0.0140649248
  },
  "aroma_motion_37": {
    "CSFFraction": 0.01,
    "EdgeFraction": 0.56,
    "HighFrequencyContent": 0.23,
    "MaximumRpCorrelation": 0.37,
    "Method": {
      "Name": "ICA-AROMA",
      "Version": "0.4.5"
    },
    "ModelVarianceExplained": 0.0154106427,
    "MotionNoise": false,
    "TotalVarianceExplained": 0.0139288868
  },
  "aroma_motion_38": {
    "CSFFraction": 0.04,
    "EdgeFraction": 0.7,
    "HighFrequencyContent": 0.33,
    "MaximumRpCorrelation": 0.32,
    "Method": {
      "Name": "ICA-AROMA",
      "Version": "0.4.5"
    },
    "ModelVarianceExplained": 0.0152113906,
    "MotionNoise": true,
    "TotalVarianceExplained": 0.0137487931
  },
  "aroma_motion_39": {
    "CSFFraction": 0.01,
    "EdgeFraction": 0.65,
    "HighFrequencyContent": 0.39,
    "MaximumRpCorrelation": 0.38,
    "Method": {
      "Name": "ICA-AROMA",
      "Version": "0.4.5"
    },
    "ModelVarianceExplained": 0.0151084234,
    "MotionNoise": true,
    "TotalVarianceExplained": 0.0136557263
  },
  "aroma_motion_4": {
    "CSFFraction": 0.01,
    "EdgeFraction": 0.15,
    "HighFrequencyContent": 0.03,
    "MaximumRpCorrelation": 0.54,
    "Method": {
      "Name": "ICA-AROMA",
      "Version": "0.4.5"
    },
    "ModelVarianceExplained": 0.0251194316,
    "MotionNoise": false,
    "TotalVarianceExplained": 0.0227041614
  },
  "aroma_motion_40": {
    "CSFFraction": 0.01,
    "EdgeFraction": 0.64,
    "HighFrequencyContent": 0.33,
    "MaximumRpCorrelation": 0.31,
    "Method": {
      "Name": "ICA-AROMA",
      "Version": "0.4.5"
    },
    "ModelVarianceExplained": 0.0149766633,
    "MotionNoise": false,
    "TotalVarianceExplained": 0.0135366352
  },
  "aroma_motion_41": {
    "CSFFraction": 0.0,
    "EdgeFraction": 0.45,
    "HighFrequencyContent": 0.07,
    "MaximumRpCorrelation": 0.46,
    "Method": {
      "Name": "ICA-AROMA",
      "Version": "0.4.5"
    },
    "ModelVarianceExplained": 0.0149312935,
    "MotionNoise": false,
    "TotalVarianceExplained": 0.0134956278
  },
  "aroma_motion_42": {
    "CSFFraction": 0.01,
    "EdgeFraction": 0.34,
    "HighFrequencyContent": 0.18,
    "MaximumRpCorrelation": 0.43,
    "Method": {
      "Name": "ICA-AROMA",
      "Version": "0.4.5"
    },
    "ModelVarianceExplained": 0.0147722682,
    "MotionNoise": false,
    "TotalVarianceExplained": 0.013351893
  },
  "aroma_motion_43": {
    "CSFFraction": 0.0,
    "EdgeFraction": 0.32,
    "HighFrequencyContent": 0.17,
    "MaximumRpCorrelation": 0.29,
    "Method": {
      "Name": "ICA-AROMA",
      "Version": "0.4.5"
    },
    "ModelVarianceExplained": 0.0146159155,
    "MotionNoise": false,
    "TotalVarianceExplained": 0.0132105738
  },
  "aroma_motion_44": {
    "CSFFraction": 0.0,
    "EdgeFraction": 0.37,
    "HighFrequencyContent": 0.11,
    "MaximumRpCorrelation": 0.34,
    "Method": {
      "Name": "ICA-AROMA",
      "Version": "0.4.5"
    },
    "ModelVarianceExplained": 0.0140865466,
    "MotionNoise": false,
    "TotalVarianceExplained": 0.0127321045
  },
  "aroma_motion_45": {
    "CSFFraction": 0.05,
    "EdgeFraction": 0.33,
    "HighFrequencyContent": 0.43,
    "MaximumRpCorrelation": 0.36,
    "Method": {
      "Name": "ICA-AROMA",
      "Version": "0.4.5"
    },
    "ModelVarianceExplained": 0.0136743092,
    "MotionNoise": true,
    "TotalVarianceExplained": 0.0123595043
  },
  "aroma_motion_46": {
    "CSFFraction": 0.0,
    "EdgeFraction": 0.16,
    "HighFrequencyContent": 0.24,
    "MaximumRpCorrelation": 0.35,
    "Method": {
      "Name": "ICA-AROMA",
      "Version": "0.4.5"
    },
    "ModelVarianceExplained": 0.0136450329,
    "MotionNoise": false,
    "TotalVarianceExplained": 0.012333043
  },
  "aroma_motion_47": {
    "CSFFraction": 0.01,
    "EdgeFraction": 0.3,
    "HighFrequencyContent": 0.22,
    "MaximumRpCorrelation": 0.29,
    "Method": {
      "Name": "ICA-AROMA",
      "Version": "0.4.5"
    },
    "ModelVarianceExplained": 0.0136231873,
    "MotionNoise": false,
    "TotalVarianceExplained": 0.0123132979
  },
  "aroma_motion_48": {
    "CSFFraction": 0.07,
    "EdgeFraction": 0.38,
    "HighFrequencyContent": 0.09,
    "MaximumRpCorrelation": 0.26,
    "Method": {
      "Name": "ICA-AROMA",
      "Version": "0.4.5"
    },
    "ModelVarianceExplained": 0.0131504988,
    "MotionNoise": false,
    "TotalVarianceExplained": 0.011886059
  },
  "aroma_motion_49": {
    "CSFFraction": 0.0,
    "EdgeFraction": 0.41,
    "HighFrequencyContent": 0.29,
    "MaximumRpCorrelation": 0.35,
    "Method": {
      "Name": "ICA-AROMA",
      "Version": "0.4.5"
    },
    "ModelVarianceExplained": 0.0130507928,
    "MotionNoise": false,
    "TotalVarianceExplained": 0.01179594
  },
  "aroma_motion_5": {
    "CSFFraction": 0.01,
    "EdgeFraction": 0.37,
    "HighFrequencyContent": 0.07,
    "MaximumRpCorrelation": 0.63,
    "Method": {
      "Name": "ICA-AROMA",
      "Version": "0.4.5"
    },
    "ModelVarianceExplained": 0.0248991842,
    "MotionNoise": false,
    "TotalVarianceExplained": 0.0225050911
  },
  "aroma_motion_50": {
    "CSFFraction": 0.01,
    "EdgeFraction": 0.2,
    "HighFrequencyContent": 0.31,
    "MaximumRpCorrelation": 0.28,
    "Method": {
      "Name": "ICA-AROMA",
      "Version": "0.4.5"
    },
    "ModelVarianceExplained": 0.0128911844,
    "MotionNoise": false,
    "TotalVarianceExplained": 0.0116516781
  },
  "aroma_motion_51": {
    "CSFFraction": 0.03,
    "EdgeFraction": 0.49,
    "HighFrequencyContent": 0.22,
    "MaximumRpCorrelation": 0.35,
    "Method": {
      "Name": "ICA-AROMA",
      "Version": "0.4.5"
    },
    "ModelVarianceExplained": 0.0123576531,
    "MotionNoise": false,
    "TotalVarianceExplained": 0.0111694467
  },
  "aroma_motion_52": {
    "CSFFraction": 0.0,
    "EdgeFraction": 0.29,
    "HighFrequencyContent": 0.08,
    "MaximumRpCorrelation": 0.37,
    "Method": {
      "Name": "ICA-AROMA",
      "Version": "0.4.5"
    },
    "ModelVarianceExplained": 0.012071599,
    "MotionNoise": false,
    "TotalVarianceExplained": 0.0109108971
  },
  "aroma_motion_53": {
    "CSFFraction": 0.01,
    "EdgeFraction": 0.59,
    "HighFrequencyContent": 0.24,
    "MaximumRpCorrelation": 0.68,
    "Method": {
      "Name": "ICA-AROMA",
      "Version": "0.4.5"
    },
    "ModelVarianceExplained": 0.0118408893,
    "MotionNoise": true,
    "TotalVarianceExplained": 0.0107023705
  },
  "aroma_motion_6": {
    "CSFFraction": 0.16,
    "EdgeFraction": 0.53,
    "HighFrequencyContent": 0.52,
    "MaximumRpCorrelation": 0.23,
    "Method": {
      "Name": "ICA-AROMA",
      "Version": "0.4.5"
    },
    "ModelVarianceExplained": 0.0247255778,
    "MotionNoise": true,
    "TotalVarianceExplained": 0.0223481772
  },
  "aroma_motion_7": {
    "CSFFraction": 0.0,
    "EdgeFraction": 0.8,
    "HighFrequencyContent": 0.31,
    "MaximumRpCorrelation": 0.56,
    "Method": {
      "Name": "ICA-AROMA",
      "Version": "0.4.5"
    },
    "ModelVarianceExplained": 0.0245891243,
    "MotionNoise": true,
    "TotalVarianceExplained": 0.0222248439
  },
  "aroma_motion_8": {
    "CSFFraction": 0.0,
    "EdgeFraction": 0.6,
    "HighFrequencyContent": 0.19,
    "MaximumRpCorrelation": 0.59,
    "Method": {
      "Name": "ICA-AROMA",
      "Version": "0.4.5"
    },
    "ModelVarianceExplained": 0.0243533391,
    "MotionNoise": true,
    "TotalVarianceExplained": 0.0220117299
  },
  "aroma_motion_9": {
    "CSFFraction": 0.01,
    "EdgeFraction": 0.56,
    "HighFrequencyContent": 0.26,
    "MaximumRpCorrelation": 0.6,
    "Method": {
      "Name": "ICA-AROMA",
      "Version": "0.4.5"
    },
    "ModelVarianceExplained": 0.0241937292,
    "MotionNoise": false,
    "TotalVarianceExplained": 0.0218674666
  },
  "c_comp_cor_00": {
    "CumulativeVarianceExplained": 0.1150181124,
    "Mask": "CSF",
    "Method": "aCompCor",
    "Retained": true,
    "SingularValue": 74.2096167726,
    "VarianceExplained": 0.1150181124
  },
  "c_comp_cor_01": {
    "CumulativeVarianceExplained": 0.2281797495,
    "Mask": "CSF",
    "Method": "aCompCor",
    "Retained": true,
    "SingularValue": 73.6082820528,
    "VarianceExplained": 0.1131616372
  },
  "c_comp_cor_02": {
    "CumulativeVarianceExplained": 0.330138005,
    "Mask": "CSF",
    "Method": "aCompCor",
    "Retained": true,
    "SingularValue": 69.8696019052,
    "VarianceExplained": 0.1019582554
  },
  "c_comp_cor_03": {
    "CumulativeVarianceExplained": 0.3969891104,
    "Mask": "CSF",
    "Method": "aCompCor",
    "Retained": true,
    "SingularValue": 56.5758864498,
    "VarianceExplained": 0.0668511054
  },
  "c_comp_cor_04": {
    "CumulativeVarianceExplained": 0.4444556364,
    "Mask": "CSF",
    "Method": "aCompCor",
    "Retained": true,
    "SingularValue": 47.6728147219,
    "VarianceExplained": 0.047466526
  },
  "c_comp_cor_05": {
    "CumulativeVarianceExplained": 0.4835551292,
    "Mask": "CSF",
    "Method": "aCompCor",
    "Retained": true,
    "SingularValue": 43.2675827183,
    "VarianceExplained": 0.0390994928
  },
  "c_comp_cor_06": {
    "CumulativeVarianceExplained": 0.5139842059,
    "Mask": "CSF",
    "Method": "aCompCor",
    "Retained": true,
    "SingularValue": 38.169938362,
    "VarianceExplained": 0.0304290767
  },
  "csf": {
    "Method": "Mean"
  },
  "csf_wm": {
    "Method": "Mean"
  },
  "global_signal": {
    "Method": "Mean"
  },
  "t_comp_cor_00": {
    "CumulativeVarianceExplained": 0.4713637522,
    "Method": "tCompCor",
    "Retained": true,
    "SingularValue": 264.1317970878,
    "VarianceExplained": 0.4713637522
  },
  "t_comp_cor_01": {
    "CumulativeVarianceExplained": 0.7493095684,
    "Method": "tCompCor",
    "Retained": true,
    "SingularValue": 202.8255515592,
    "VarianceExplained": 0.2779458162
  },
  "tcompcor": {
    "Method": "Mean"
  },
  "w_comp_cor_00": {
    "CumulativeVarianceExplained": 0.0583031647,
    "Mask": "WM",
    "Method": "aCompCor",
    "Retained": true,
    "SingularValue": 76.2770569033,
    "VarianceExplained": 0.0583031647
  },
  "w_comp_cor_01": {
    "CumulativeVarianceExplained": 0.1027353934,
    "Mask": "WM",
    "Method": "aCompCor",
    "Retained": true,
    "SingularValue": 66.5881443621,
    "VarianceExplained": 0.0444322287
  },
  "w_comp_cor_02": {
    "CumulativeVarianceExplained": 0.1283714509,
    "Mask": "WM",
    "Method": "aCompCor",
    "Retained": true,
    "SingularValue": 50.5793776662,
    "VarianceExplained": 0.0256360575
  },
  "w_comp_cor_03": {
    "CumulativeVarianceExplained": 0.1528560559,
    "Mask": "WM",
    "Method": "aCompCor",
    "Retained": true,
    "SingularValue": 49.4304330094,
    "VarianceExplained": 0.0244846051
  },
  "w_comp_cor_04": {
    "CumulativeVarianceExplained": 0.1743343045,
    "Mask": "WM",
    "Method": "aCompCor",
    "Retained": true,
    "SingularValue": 46.2964078586,
    "VarianceExplained": 0.0214782486
  },
  "w_comp_cor_05": {
    "CumulativeVarianceExplained": 0.1946070497,
    "Mask": "WM",
    "Method": "aCompCor",
    "Retained": true,
    "SingularValue": 44.9784147731,
    "VarianceExplained": 0.0202727453
  },
  "w_comp_cor_06": {
    "CumulativeVarianceExplained": 0.2132497322,
    "Mask": "WM",
    "Method": "aCompCor",
    "Retained": true,
    "SingularValue": 43.1322451146,
    "VarianceExplained": 0.0186426825
  },
  "w_comp_cor_07": {
    "CumulativeVarianceExplained": 0.2296592505,
    "Mask": "WM",
    "Method": "aCompCor",
    "Retained": true,
    "SingularValue": 40.466512649,
    "VarianceExplained": 0.0164095183
  },
  "w_comp_cor_08": {
    "CumulativeVarianceExplained": 0.2437918361,
    "Mask": "WM",
    "Method": "aCompCor",
    "Retained": true,
    "SingularValue": 37.5542139255,
    "VarianceExplained": 0.0141325856
  },
  "w_comp_cor_09": {
    "CumulativeVarianceExplained": 0.2572520397,
    "Mask": "WM",
    "Method": "aCompCor",
    "Retained": true,
    "SingularValue": 36.6499746758,
    "VarianceExplained": 0.0134602037
  },
  "w_comp_cor_10": {
    "CumulativeVarianceExplained": 0.2706024121,
    "Mask": "WM",
    "Method": "aCompCor",
    "Retained": true,
    "SingularValue": 36.5001418499,
    "VarianceExplained": 0.0133503723
  },
  "w_comp_cor_11": {
    "CumulativeVarianceExplained": 0.2833406127,
    "Mask": "WM",
    "Method": "aCompCor",
    "Retained": true,
    "SingularValue": 35.6534782745,
    "VarianceExplained": 0.0127382006
  },
  "w_comp_cor_12": {
    "CumulativeVarianceExplained": 0.2954430788,
    "Mask": "WM",
    "Method": "aCompCor",
    "Retained": true,
    "SingularValue": 34.752399963,
    "VarianceExplained": 0.0121024662
  },
  "w_comp_cor_13": {
    "CumulativeVarianceExplained": 0.30713017,
    "Mask": "WM",
    "Method": "aCompCor",
    "Retained": true,
    "SingularValue": 34.1508156075,
    "VarianceExplained": 0.0116870912
  },
  "w_comp_cor_14": {
    "CumulativeVarianceExplained": 0.3180162386,
    "Mask": "WM",
    "Method": "aCompCor",
    "Retained": true,
    "SingularValue": 32.9597111158,
    "VarianceExplained": 0.0108860686
  },
  "w_comp_cor_15": {
    "CumulativeVarianceExplained": 0.3286941748,
    "Mask": "WM",
    "Method": "aCompCor",
    "Retained": true,
    "SingularValue": 32.6431096676,
    "VarianceExplained": 0.0106779362
  },
  "w_comp_cor_16": {
    "CumulativeVarianceExplained": 0.3393044748,
    "Mask": "WM",
    "Method": "aCompCor",
    "Retained": true,
    "SingularValue": 32.5395614616,
    "VarianceExplained": 0.0106103
  },
  "w_comp_cor_17": {
    "CumulativeVarianceExplained": 0.3496830999,
    "Mask": "WM",
    "Method": "aCompCor",
    "Retained": true,
    "SingularValue": 32.1823515934,
    "VarianceExplained": 0.0103786251
  },
  "w_comp_cor_18": {
    "CumulativeVarianceExplained": 0.3598190514,
    "Mask": "WM",
    "Method": "aCompCor",
    "Retained": true,
    "SingularValue": 31.8038814121,
    "VarianceExplained": 0.0101359515
  },
  "w_comp_cor_19": {
    "CumulativeVarianceExplained": 0.3695357776,
    "Mask": "WM",
    "Method": "aCompCor",
    "Retained": true,
    "SingularValue": 31.1392283437,
    "VarianceExplained": 0.0097167262
  },
  "w_comp_cor_20": {
    "CumulativeVarianceExplained": 0.3790815004,
    "Mask": "WM",
    "Method": "aCompCor",
    "Retained": true,
    "SingularValue": 30.8640042876,
    "VarianceExplained": 0.0095457227
  },
  "w_comp_cor_21": {
    "CumulativeVarianceExplained": 0.3884863645,
    "Mask": "WM",
    "Method": "aCompCor",
    "Retained": true,
    "SingularValue": 30.6354403542,
    "VarianceExplained": 0.0094048642
  },
  "w_comp_cor_22": {
    "CumulativeVarianceExplained": 0.3977187453,
    "Mask": "WM",
    "Method": "aCompCor",
    "Retained": true,
    "SingularValue": 30.3532163203,
    "VarianceExplained": 0.0092323808
  },
  "w_comp_cor_23": {
    "CumulativeVarianceExplained": 0.4069068165,
    "Mask": "WM",
    "Method": "aCompCor",
    "Retained": true,
    "SingularValue": 30.2802906828,
    "VarianceExplained": 0.0091880712
  },
  "w_comp_cor_24": {
    "CumulativeVarianceExplained": 0.4159237343,
    "Mask": "WM",
    "Method": "aCompCor",
    "Retained": true,
    "SingularValue": 29.9969374886,
    "VarianceExplained": 0.0090169178
  },
  "w_comp_cor_25": {
    "CumulativeVarianceExplained": 0.4247735344,
    "Mask": "WM",
    "Method": "aCompCor",
    "Retained": true,
    "SingularValue": 29.7176589895,
    "VarianceExplained": 0.0088498001
  },
  "w_comp_cor_26": {
    "CumulativeVarianceExplained": 0.4335401049,
    "Mask": "WM",
    "Method": "aCompCor",
    "Retained": true,
    "SingularValue": 29.5775861576,
    "VarianceExplained": 0.0087665705
  },
  "w_comp_cor_27": {
    "CumulativeVarianceExplained": 0.4421991637,
    "Mask": "WM",
    "Method": "aCompCor",
    "Retained": true,
    "SingularValue": 29.3956593615,
    "VarianceExplained": 0.0086590587
  },
  "w_comp_cor_28": {
    "CumulativeVarianceExplained": 0.4507268591,
    "Mask": "WM",
    "Method": "aCompCor",
    "Retained": true,
    "SingularValue": 29.1718319773,
    "VarianceExplained": 0.0085276954
  },
  "w_comp_cor_29": {
    "CumulativeVarianceExplained": 0.4591816993,
    "Mask": "WM",
    "Method": "aCompCor",
    "Retained": true,
    "SingularValue": 29.0469519179,
    "VarianceExplained": 0.0084548402
  },
  "w_comp_cor_30": {
    "CumulativeVarianceExplained": 0.4674517379,
    "Mask": "WM",
    "Method": "aCompCor",
    "Retained": true,
    "SingularValue": 28.7277512042,
    "VarianceExplained": 0.0082700386
  },
  "w_comp_cor_31": {
    "CumulativeVarianceExplained": 0.4756176768,
    "Mask": "WM",
    "Method": "aCompCor",
    "Retained": true,
    "SingularValue": 28.5463724472,
    "VarianceExplained": 0.008165939
  },
  "w_comp_cor_32": {
    "CumulativeVarianceExplained": 0.4837181841,
    "Mask": "WM",
    "Method": "aCompCor",
    "Retained": true,
    "SingularValue": 28.4317747738,
    "VarianceExplained": 0.0081005072
  },
  "w_comp_cor_33": {
    "CumulativeVarianceExplained": 0.4916470667,
    "Mask": "WM",
    "Method": "aCompCor",
    "Retained": true,
    "SingularValue": 28.1289718791,
    "VarianceExplained": 0.0079288827
  },
  "w_comp_cor_34": {
    "CumulativeVarianceExplained": 0.4995074003,
    "Mask": "WM",
    "Method": "aCompCor",
    "Retained": true,
    "SingularValue": 28.0071135122,
    "VarianceExplained": 0.0078603336
  },
  "w_comp_cor_35": {
    "CumulativeVarianceExplained": 0.507209162,
    "Mask": "WM",
    "Method": "aCompCor",
    "Retained": true,
    "SingularValue": 27.7231708703,
    "VarianceExplained": 0.0077017617
  },
  "white_matter": {
    "Method": "Mean"
  }
}